cenv_script/__init__.py
cenv_script/cenv_script.py
cenv_script/cli.py
cenv_script-0.0.2.dist-info/AUTHORS.rst
cenv_script-0.0.2.dist-info/LICENSE
cenv_script-0.0.2.dist-info/METADATA
cenv_script-0.0.2.dist-info/WHEEL
cenv_script-0.0.2.dist-info/entry_points.txt
cenv_script-0.0.2.dist-info/top_level.txt
cenv_script-0.0.2.dist-info/RECORD
