Metadata-Version: 2.1
Name: cenv-script
Version: 0.0.2
Summary: Wrapper around conda that automatically persists changes to environment.yml, inspired by pipenv
Home-page: https://github.com/technic/cenv_script
Author: Alex Maystrenko
Author-email: alexeytech@gmail.com
License: MIT license
Keywords: cenv_script
Platform: UNKNOWN
Classifier: Development Status :: 2 - Pre-Alpha
Classifier: Intended Audience :: Developers
Classifier: License :: OSI Approved :: MIT License
Classifier: Natural Language :: English
Classifier: Programming Language :: Python :: 3
Classifier: Programming Language :: Python :: 3.6
Classifier: Programming Language :: Python :: 3.7
Classifier: Programming Language :: Python :: 3.8
Requires-Python: >=3.6
Requires-Dist: Click (>=7.0)
Requires-Dist: pyyaml (>=5.3.1)
